webfast/__init__.py
webfast/constants.py
webfast/version.py
webfast/webfast.py
webfast-1.1.1.dist-info/LICENSE
webfast-1.1.1.dist-info/METADATA
webfast-1.1.1.dist-info/WHEEL
webfast-1.1.1.dist-info/top_level.txt
webfast-1.1.1.dist-info/RECORD
