Metadata-Version: 2.1
Name: webfast
Version: 1.1.1
Summary: Fast HTML Abstraction and Generator for Python
Home-page: https://github.com/rmaniego/webfast
Author: Rodney Maniego Jr.
Author-email: rod.maniego23@gmail.com
License: MIT
Download-URL: https://github.com/rmaniego/webfast/archive/v1.0.tar.gz
Keywords: html,abstraction,template,python
Platform: UNKNOWN
Classifier: Development Status :: 5 - Production/Stable
Classifier: Intended Audience :: Developers
Classifier: Topic :: Software Development :: Build Tools
Classifier: License :: OSI Approved :: MIT License
Classifier: Programming Language :: Python :: 3
Requires-Python: >=3.9
License-File: LICENSE
Requires-Dist: arkivist
Requires-Dist: lxml
Requires-Dist: namari
